traccess/__init__.py
traccess/access.py
traccess/data.py
traccess/exception.py
traccess-0.0.2.dist-info/LICENSE
traccess-0.0.2.dist-info/METADATA
traccess-0.0.2.dist-info/WHEEL
traccess-0.0.2.dist-info/top_level.txt
traccess-0.0.2.dist-info/RECORD
