Metadata-Version: 2.1
Name: traccess
Version: 0.0.2
Summary: Transportation access to opportunities and equity analysis
Author: Willem Klumpenhouwer
Author-email: willem@klumpentown.com
License: MIT
License-File: LICENSE
Requires-Dist: pandas >=2.0
